nokogiri/__init__.py
nokogiri/anyparse.py
nokogiri/cell.py
nokogiri/curry.py
nokogiri/defaultdotdict.py
nokogiri/helloworld.py
nokogiri/shared_map.py
nokogiri/spylus.py
nokogiri/tqdm_load.py
nokogiri/which_env.py
nokogiri/working_dir.py
tests/__init__.py
tests/test_cell.py
tests/test_curry.py
tests/test_tqdm_load.py
tests/test_which_env.py
tests/test_working_dir.py
nokogiri-0.2.2.dist-info/LICENSE
nokogiri-0.2.2.dist-info/METADATA
nokogiri-0.2.2.dist-info/WHEEL
nokogiri-0.2.2.dist-info/top_level.txt
nokogiri-0.2.2.dist-info/RECORD
