Metadata-Version: 2.1
Name: nokogiri
Version: 0.2.2
Summary: UNKNOWN
Home-page: https://github.com/nat-chan/nokogiri
License: UNKNOWN
Platform: UNKNOWN
License-File: LICENSE
